setup.cfg
setup.py
sauce/__init__.py
sauce/jobs.py
sauce/sauce.py
sauce/tunnels.py
saucelabs_python.egg-info/PKG-INFO
saucelabs_python.egg-info/SOURCES.txt
saucelabs_python.egg-info/dependency_links.txt
saucelabs_python.egg-info/requires.txt
saucelabs_python.egg-info/top_level.txt