Metadata-Version: 1.1
Name: saucelabs-python
Version: 0.2
Summary: REST Client for Saucelabs API
Home-page: https://github.com/maudineormsby/saucelabs-python
Author: Jason Carr
Author-email: jason.s.carr@gmail.com
License: Apache 2.0
Keywords: sauce,saucelabs,rest,development,python client,automation,selenium,webdriver
Platform: UNKNOWN
Classifier: Development Status :: 3 - Alpha
Classifier: Intended Audience :: Developers
Classifier: License :: OSI Approved :: Apache Software License
Classifier: Programming Language :: Python :: 2
Classifier: Programming Language :: Python :: 2.6
Classifier: Programming Language :: Python :: 2.7
